snipssmartercoffee/Snipsspec
snipssmartercoffee/__init__.py
snipssmartercoffee/snipssmartercoffee.py
snipssmartercoffee-1.0.dist-info/DESCRIPTION.rst
snipssmartercoffee-1.0.dist-info/METADATA
snipssmartercoffee-1.0.dist-info/RECORD
snipssmartercoffee-1.0.dist-info/WHEEL
snipssmartercoffee-1.0.dist-info/metadata.json
snipssmartercoffee-1.0.dist-info/top_level.txt
