Metadata-Version: 2.0
Name: snipssmartercoffee
Version: 1.0
Summary: Smarter Coffee skill for Snips
Home-page: https://github.com/snipsco/snips-skill-smarter-coffee
Author: Michael Fester
Author-email: michael.fester@gmail.com
License: MIT
Keywords: snips
Platform: UNKNOWN
